prpc_python/__api.py
prpc_python/__init__.py
prpc_python/cli.py
prpc_python/flask/__api.py
prpc_python/flask/__app.py
prpc_python/flask/__init__.py
prpc_python/flask/__templates/index.html
prpc_python/pyodide.py
prpc_python/sample.py
prpc_python-0.9.2.dist-info/entry_points.txt
prpc_python-0.9.2.dist-info/WHEEL
prpc_python-0.9.2.dist-info/METADATA
prpc_python-0.9.2.dist-info/RECORD
